grave_settings/__init__.py
grave_settings/abstract.py
grave_settings/base.py
grave_settings/config_file.py
grave_settings/conversion_manager.py
grave_settings/default_handlers.py
grave_settings/formatter.py
grave_settings/formatter_settings.py
grave_settings/framestack_context.py
grave_settings/handlers.py
grave_settings/helper_objects.py
grave_settings/semantics.py
grave_settings/utilities.py
grave_settings/validation.py
grave_settings/formatters/__init__.py
grave_settings/formatters/bson.py
grave_settings/formatters/json.py
grave_settings/formatters/toml.py
grave_settings-0.1.4.dist-info/LICENSE
grave_settings-0.1.4.dist-info/METADATA
grave_settings-0.1.4.dist-info/WHEEL
grave_settings-0.1.4.dist-info/top_level.txt
grave_settings-0.1.4.dist-info/RECORD
