Metadata-Version: 2.1
Name: grave-settings
Version: 0.1.4
Summary: A library for automatic serialization of python object hierarchies to storage
Home-page: https://github.com/ILikesCaviar/GraveSettings
Author: Ryan McConnell
Classifier: Programming Language :: Python :: 3
Classifier: License :: OSI Approved :: MIT License
Classifier: Operating System :: OS Independent
Requires-Python: >=3.0
License-File: LICENSE
Requires-Dist: ordered-set (>=4.1.0)
Requires-Dist: observer-hooks (>=1.3.0)
